edc/__init__.py
edc-1.2.7.dist-info/licenses/LICENSE
edc-1.2.7.dist-info/WHEEL
edc-1.2.7.dist-info/METADATA
edc-1.2.7.dist-info/RECORD
