Metadata-Version: 2.4
Name: edc
Version: 1.2.7
Summary: EDC core modules for clinicedc/edc projects
Keywords: django,clinicedc,edc,clinical trials,research,data management,esource
Author: Erik van Widenfelt, Jonathan Willitts
Author-email: Erik van Widenfelt <ew2789@gmail.com>, Jonathan Willitts <j.willitts@ucl.ac.uk>
License-Expression: GPL-3.0-or-later
License-File: LICENSE
Classifier: Environment :: Web Environment
Classifier: Framework :: Django
Classifier: Framework :: Django :: 5.2
Classifier: Development Status :: 5 - Production/Stable
Classifier: Intended Audience :: Developers
Classifier: Intended Audience :: Science/Research
Classifier: Operating System :: OS Independent
Classifier: Programming Language :: Python :: 3.12
Classifier: Programming Language :: Python :: 3.13
Requires-Dist: django==5.2.4
Requires-Dist: boto3>=1.39.15
Requires-Dist: django-db-views>=0.1.11
Requires-Dist: django-defender>=0.9.8
Requires-Dist: django-environ>=0.12.0
Requires-Dist: django-logentry-admin>=1.1.0
Requires-Dist: django-admin-rangefilter>=0.13.3
Requires-Dist: django-pandas>=0.6.7
Requires-Dist: django-redis>=6.0.0
Requires-Dist: django-simple-history>=3.10.1
Requires-Dist: django-storages>=1.14.6
Requires-Dist: djangorestframework>=3.16.0
Requires-Dist: fontawesomefree>=6.6.0
Requires-Dist: gunicorn>=23.0.0
Requires-Dist: pyrabbit>=1.1.0
Requires-Dist: python-memcached>=1.62
Requires-Dist: django-audit-fields>=1.1.0
Requires-Dist: django-crypto-fields>=1.0.1
Requires-Dist: django-multisite2>=2.1.0
Requires-Dist: django-revision>=1.0.0
Requires-Dist: edc-action-item==1.0.3
Requires-Dist: edc-adherence==1.0.1
Requires-Dist: edc-adverse-event==1.0.3
Requires-Dist: edc-analytics==0.1.4
Requires-Dist: edc-appconfig==1.0.2
Requires-Dist: edc-appointment==1.1.1
Requires-Dist: edc-auth==1.0.2
Requires-Dist: edc-consent==1.0.3
Requires-Dist: edc-constants==1.0.1
Requires-Dist: edc-crf==1.0.2
Requires-Dist: edc-dashboard==1.0.3
Requires-Dist: edc-data-manager==1.0.0
Requires-Dist: edc-device==1.0.1
Requires-Dist: edc-document-status==1.0.0
Requires-Dist: edc-dx==1.0.1
Requires-Dist: edc-dx-review==1.0.1
Requires-Dist: edc-egfr==1.0.2
Requires-Dist: edc-export==1.0.4
Requires-Dist: edc-facility==1.0.2
Requires-Dist: edc-fieldsets==1.0.1
Requires-Dist: edc-form-describer==1.0.2
Requires-Dist: edc-form-label==1.0.2
Requires-Dist: edc-form-runners==1.0.0
Requires-Dist: edc-form-validators==1.0.0
Requires-Dist: edc-glucose==1.0.3
Requires-Dist: edc-he==1.0.2
Requires-Dist: edc-identifier==1.0.0
Requires-Dist: edc-lab==1.0.5
Requires-Dist: edc-lab-dashboard==1.0.2
Requires-Dist: edc-lab-panel==1.0.0
Requires-Dist: edc-lab-results==1.0.2
Requires-Dist: edc-label==1.0.0
Requires-Dist: edc-list-data==1.0.0
Requires-Dist: edc-listboard==1.0.0
Requires-Dist: edc-locator==1.0.2
Requires-Dist: edc-ltfu==1.0.1
Requires-Dist: edc-metadata==1.0.5
Requires-Dist: edc-microbiology==1.0.0
Requires-Dist: edc-microscopy==1.0.0
Requires-Dist: edc-mnsi==1.0.0
Requires-Dist: edc-model==1.0.0
Requires-Dist: edc-model-admin==1.0.3
Requires-Dist: edc-model-fields==1.0.0
Requires-Dist: edc-model-form==1.0.0
Requires-Dist: edc-model-to-dataframe==1.0.1
Requires-Dist: edc-navbar==1.0.0
Requires-Dist: edc-next-appointment==0.3.1
Requires-Dist: edc-notification==1.0.1
Requires-Dist: edc-offstudy==1.0.1
Requires-Dist: edc-pdf-reports==1.0.2
Requires-Dist: edc-pdutils==1.0.2
Requires-Dist: edc-pharmacy==1.2.3
Requires-Dist: edc-prn==1.1.1
Requires-Dist: edc-protocol==1.0.1
Requires-Dist: edc-protocol-incident==1.0.1
Requires-Dist: edc-pylabels==1.0.1
Requires-Dist: edc-qareports==1.0.4
Requires-Dist: edc-qol==1.0.2
Requires-Dist: edc-randomization==1.0.4
Requires-Dist: edc-refusal==1.0.1
Requires-Dist: edc-registration==1.0.1
Requires-Dist: edc-reportable==2.0.2
Requires-Dist: edc-review-dashboard==1.0.2
Requires-Dist: edc-rx==1.0.1
Requires-Dist: edc-screening==1.1.0
Requires-Dist: edc-search==1.0.1
Requires-Dist: edc-sites==1.1.0
Requires-Dist: edc-subject-dashboard==1.0.1
Requires-Dist: edc-timepoint==1.0.1
Requires-Dist: edc-transfer==1.0.1
Requires-Dist: edc-unblinding==1.0.2
Requires-Dist: edc-utils==1.1.1
Requires-Dist: edc-view-utils==1.0.1
Requires-Dist: edc-visit-schedule==4.1.1
Requires-Dist: edc-visit-tracking==1.0.2
Requires-Dist: edc-vitals==1.1.2
Requires-Dist: aiohappyeyeballs>=2.6.1
Requires-Dist: aiohttp>=3.12.15
Requires-Dist: aiohttp-retry>=2.9.1
Requires-Dist: aiosignal>=1.4.0
Requires-Dist: amqp>=5.3.1
Requires-Dist: arrow>=1.3.0
Requires-Dist: asgiref>=3.9.1
Requires-Dist: attrs>=25.3.0
Requires-Dist: beautifulsoup4>=4.13.4
Requires-Dist: billiard>=4.2.1
Requires-Dist: botocore>=1.39.16
Requires-Dist: celery>=5.5.3
Requires-Dist: certifi>=2025.7.14
Requires-Dist: cffi>=1.17.1
Requires-Dist: charset-normalizer>=3.4.2
Requires-Dist: click>=8.2.1
Requires-Dist: click-didyoumean>=0.3.1
Requires-Dist: click-plugins>=1.1.1.2
Requires-Dist: click-repl>=0.3.0
Requires-Dist: cryptography>=45.0.5
Requires-Dist: django-extensions>=4.1
Requires-Dist: django-pylabels>=1.0.1
Requires-Dist: django-sequences>=3.0
Requires-Dist: filelock>=3.18.0
Requires-Dist: frozenlist>=1.7.0
Requires-Dist: gitdb>=4.0.12
Requires-Dist: gitpython>=3.1.45
Requires-Dist: httplib2>=0.22.0
Requires-Dist: idna>=3.10
Requires-Dist: inflect>=7.5.0
Requires-Dist: jmespath>=1.0.1
Requires-Dist: kombu>=5.5.4
Requires-Dist: mempass>=0.1.2
Requires-Dist: more-itertools>=10.7.0
Requires-Dist: multidict>=6.6.3
Requires-Dist: mysqlclient>=2.2.7
Requires-Dist: numpy>=2.3.2
Requires-Dist: packaging>=25.0
Requires-Dist: pandas>=2.3.1
Requires-Dist: pillow>=11.3.0
Requires-Dist: prompt-toolkit>=3.0.51
Requires-Dist: propcache>=0.3.2
Requires-Dist: pycparser>=2.22
Requires-Dist: pycryptodomex>=3.23.0
Requires-Dist: pycups>=2.0.4
Requires-Dist: pyjwt>=2.10.1
Requires-Dist: pylabels2>=1.4.4
Requires-Dist: pyparsing>=3.2.3
Requires-Dist: pypdf>=5.9.0
Requires-Dist: python-dateutil>=2.9.0.post0
Requires-Dist: pytz>=2025.2
Requires-Dist: redis>=6.2.0
Requires-Dist: reportlab>=4.4.3
Requires-Dist: requests>=2.32.4
Requires-Dist: requests-file>=2.1.0
Requires-Dist: s3transfer>=0.13.1
Requires-Dist: six>=1.17.0
Requires-Dist: smmap>=5.0.2
Requires-Dist: soupsieve>=2.7
Requires-Dist: sqlalchemy>=2.0.42
Requires-Dist: sqlglot>=27.4.1
Requires-Dist: sqlglotrs>=0.6.1
Requires-Dist: sqlparse>=0.5.3
Requires-Dist: tldextract>=5.3.0
Requires-Dist: tqdm>=4.67.1
Requires-Dist: twilio>=9.7.0
Requires-Dist: typeguard>=4.4.4
Requires-Dist: types-python-dateutil>=2.9.0.20250708
Requires-Dist: typing-extensions>=4.14.1
Requires-Dist: tzdata>=2025.2
Requires-Dist: urllib3>=2.5.0
Requires-Dist: vine>=5.1.0
Requires-Dist: wcwidth>=0.2.13
Requires-Dist: yarl>=1.20.1
Requires-Dist: zxcvbn>=4.5.0
Maintainer: Erik van Widenfelt
Maintainer-email: Erik van Widenfelt <ew2789@gmail.com>
Requires-Python: >=3.12
Project-URL: Changelog, https://github.com/clinicedc/edc/blob/main/CHANGES
Project-URL: Documentation, https://github.com/clinicedc/edc/docs
Project-URL: Homepage, https://github.com/clinicedc
Project-URL: Repository, https://github.com/clinicedc/edc.git
